hystorian/__init__.py
hystorian/io/ardf_files.py
hystorian/io/csv_files.py
hystorian/io/gsf_files.py
hystorian/io/ibw_files.py
hystorian/io/img_files.py
hystorian/io/nanoscope_files.py
hystorian/io/read_file.py
hystorian/io/shg_files.py
hystorian/io/sxm_files.py
hystorian/io/xrdml_files.py
hystorian/processing/core.py
hystorian/processing/deprecated.py
hystorian/processing/experimental.py
hystorian/processing/ndim.py
hystorian/processing/plot.py
hystorian/processing/twodim.py
hystorian-1.0.5.2.dist-info/LICENSE
hystorian-1.0.5.2.dist-info/METADATA
hystorian-1.0.5.2.dist-info/WHEEL
hystorian-1.0.5.2.dist-info/top_level.txt
hystorian-1.0.5.2.dist-info/RECORD
