Metadata-Version: 2.1
Name: hystorian
Version: 1.0.5.2
Summary: a generic materials science data analysis Python package built with processing traceability, reproducibility, and archival ability at its core.
Home-page: https://gitlab.unige.ch/paruch-group/hystorian
Author: Loïc Musy <loic.musy@unige.ch>, Ralph Bulanadi <ralph.bulanadi@unige.ch>
Author-email: loic.musy@unige.ch
Classifier: Programming Language :: Python :: 3
Classifier: Operating System :: OS Independent
Requires-Python: >=3.6
License-File: LICENSE
Requires-Dist: h5py (<3,>2)
Requires-Dist: numpy (>=1.18)
Requires-Dist: igor
Requires-Dist: pillow (>7)
Requires-Dist: scipy
Requires-Dist: scikit-image
